pystooq
