Metadata-Version: 2.1
Name: pystooq
Version: 1.0.3
Summary: Package for fetching of data from Stooq.com
Home-page: UNKNOWN
Author: Artur Wegrzyn
License: UNKNOWN
Platform: UNKNOWN
License-File: LICENSE.txt
